formatData/__init__.py
formatData/httpResponce.py
formatData-1.0.dist-info/LICENSE
formatData-1.0.dist-info/METADATA
formatData-1.0.dist-info/WHEEL
formatData-1.0.dist-info/top_level.txt
formatData-1.0.dist-info/RECORD
