Metadata-Version: 2.1
Name: formatData
Version: 1.0
Summary: 这是一个关于python web 后端json数据返回的工具
Home-page: https://github.com/strongxiuxiu/formatData.git
Author: panxiuqiang
Author-email: 501274367@qq.com
License: UNKNOWN
Platform: UNKNOWN
Classifier: Programming Language :: Python :: 3
Classifier: License :: OSI Approved :: MIT License
Classifier: Operating System :: OS Independent
Requires-Python: >=3
